eet_toolkit/__init__.py
eet_toolkit/redmail.py
eet_toolkit/redmailer_gui.py
eet_toolkit/samples/accounts.json
eet_toolkit/samples/oauth2_tokens.json
eet_toolkit/samples/targets.txt
eet_toolkit/samples/template.html
eet_toolkit-1.0.3.dist-info/METADATA
eet_toolkit-1.0.3.dist-info/WHEEL
eet_toolkit-1.0.3.dist-info/entry_points.txt
eet_toolkit-1.0.3.dist-info/top_level.txt
eet_toolkit-1.0.3.dist-info/RECORD
