Metadata-Version: 2.4
Name: eet-toolkit
Version: 1.0.3
Summary: Email Enumeration Toolkit with GUI interfaces
Home-page: https://github.com/script1337/eet-toolkit
Author: Script1337
Author-email: your.email@example.com
Classifier: Programming Language :: Python :: 3
Classifier: License :: OSI Approved :: MIT License
Classifier: Operating System :: OS Independent
Requires-Python: >=3.11
Requires-Dist: PyQt6
Requires-Dist: imaplib2
Requires-Dist: jinja2
Requires-Dist: pyyaml
Requires-Dist: PySocks
Dynamic: author
Dynamic: author-email
Dynamic: classifier
Dynamic: description
Dynamic: description-content-type
Dynamic: home-page
Dynamic: requires-dist
Dynamic: requires-python
Dynamic: summary
